go_judge/__init__.py
go_judge/client.py
go_judge/image.py
go_judge/py.typed
go_judge/sandbox.py
go_judge/utils.py
go_judge-0.1.0.dist-info/WHEEL
go_judge-0.1.0.dist-info/METADATA
go_judge-0.1.0.dist-info/RECORD
