Metadata-Version: 2.3
Name: go-judge
Version: 0.1.0
Summary: Light-weight sandboxed environment powered by Linux containers
Author: criyle
Author-email: criyle <i@goj.ac>
Requires-Dist: pytest>=9.0.2
Requires-Dist: requests>=2.31.0
Requires-Dist: tqdm>=4.66.0
Requires-Python: >=3.10
